jrnl/__init__.py
jrnl/config.py
jrnl/constants.py
jrnl/grep_wrapper.py
jrnl/helpers.py
jrnl/journal.py
jrnl/main.py
jrnl/runtime_args.py
jrnl/version.py
jrnl_mw-1.4.1.data/data/usr/local/man/man1/jrnl.1
jrnl_mw-1.4.1.dist-info/METADATA
jrnl_mw-1.4.1.dist-info/WHEEL
jrnl_mw-1.4.1.dist-info/entry_points.txt
jrnl_mw-1.4.1.dist-info/licenses/LICENSE
jrnl_mw-1.4.1.dist-info/RECORD
