Metadata-Version: 2.4
Name: jrnl-mw
Version: 1.4.1
Summary: Write a journal
Project-URL: Homepage, https://github.com/mwiens91/jrnl
Project-URL: Documentation, https://github.com/mwiens91/jrnl#readme
Project-URL: Issues, https://github.com/mwiens91/jrnl/issues
Project-URL: Source, https://github.com/mwiens91/jrnl
Author-email: Matt Wiens <mwiens91@gmail.com>
Maintainer-email: Matt Wiens <mwiens91@gmail.com>
License-Expression: MIT
License-File: LICENSE
Classifier: Development Status :: 5 - Production/Stable
Classifier: Intended Audience :: End Users/Desktop
Classifier: License :: OSI Approved :: MIT License
Classifier: Natural Language :: English
Classifier: Operating System :: Unix
Classifier: Programming Language :: Python
Classifier: Programming Language :: Python :: 3
Classifier: Programming Language :: Python :: 3 :: Only
Requires-Python: >=3.10
Requires-Dist: python-dateutil
Requires-Dist: pyyaml
